comala/__init__.py
comala/workflows/__init__.py
comala/workflows/client.py
comala/workflows/models/__init__.py
comala/workflows/models/workflow.py
comala/workflows/models/workflowstate.py
comala/workflows/models/workflowtask.py
comala_workflows-0.5.1.dist-info/DESCRIPTION.rst
comala_workflows-0.5.1.dist-info/METADATA
comala_workflows-0.5.1.dist-info/RECORD
comala_workflows-0.5.1.dist-info/WHEEL
comala_workflows-0.5.1.dist-info/metadata.json
comala_workflows-0.5.1.dist-info/top_level.txt
tests/models/__init__.py
tests/models/test_workflow.py
